sat_downloaders/__init__.py
sat_downloaders/datastore.py
sat_downloaders/dhus.py
sat_downloaders/tests/__init__.py
sat_downloaders/tests/test_dhus.py
sat_downloaders-0.0.4.dist-info/LICENSE
sat_downloaders-0.0.4.dist-info/WHEEL
sat_downloaders-0.0.4.dist-info/METADATA
sat_downloaders-0.0.4.dist-info/RECORD
