Metadata-Version: 2.1
Name: sat-downloaders
Version: 0.0.4
Summary: 
License: GPLv3
Author: Martin Raspaud
Author-email: martin.raspaud@smhi.se
Requires-Python: >=3.8,<4
Classifier: License :: Other/Proprietary License
Classifier: Programming Language :: Python :: 3
Classifier: Programming Language :: Python :: 3.8
Classifier: Programming Language :: Python :: 3.9
Classifier: Programming Language :: Python :: 3.10
Requires-Dist: requests (>=2.28.1)
